ds_future_sales_2024/__init__.py
ds_future_sales_2024/data_handling.py
ds_future_sales_2024/explainability.py
ds_future_sales_2024/feature_extraction.py
ds_future_sales_2024/hyperopt.py
ds_future_sales_2024/model_training.py
ds_future_sales_2024/validation.py
ds_future_sales_2024-0.1.2.dist-info/LICENSE
ds_future_sales_2024-0.1.2.dist-info/METADATA
ds_future_sales_2024-0.1.2.dist-info/WHEEL
ds_future_sales_2024-0.1.2.dist-info/top_level.txt
ds_future_sales_2024-0.1.2.dist-info/RECORD
